{
  "project_info": {
    "project_number": "895324165265",
    "project_id": "toptop-app-d7d14",
    "storage_bucket": "toptop-app-d7d14.firebasestorage.app"
  },
  "client": [
    {
      "client_info": {
        "mobilesdk_app_id": "1:895324165265:android:e805014b91d29ca0979b30",
        "android_client_info": {
          "package_name": "com.example.tiktokcloneproject"
        }
      },
      "oauth_client": [],
      "api_key": [
        {
          "current_key": "AIzaSyBXB-D1YpdirXZJoZ_zT6BRtwIMhMW3H3M"
        }
      ],
      "services": {
        "appinvite_service": {
          "other_platform_oauth_client": []
        }
      }
    }
  ],
  "configuration_version": "1"
}